{
  "hash": "5a6fa09c",
  "configHash": "9aadfe76",
  "lockfileHash": "6638524f",
  "browserHash": "fcb4ac18",
  "optimized": {
    "react": {
      "src": "../../node_modules/react/index.js",
      "file": "react.js",
      "fileHash": "a1f4e134",
      "needsInterop": true
    },
    "react-dom": {
      "src": "../../node_modules/react-dom/index.js",
      "file": "react-dom.js",
      "fileHash": "fa720554",
      "needsInterop": true
    },
    "react/jsx-dev-runtime": {
      "src": "../../node_modules/react/jsx-dev-runtime.js",
      "file": "react_jsx-dev-runtime.js",
      "fileHash": "1df85089",
      "needsInterop": true
    },
    "react/jsx-runtime": {
      "src": "../../node_modules/react/jsx-runtime.js",
      "file": "react_jsx-runtime.js",
      "fileHash": "bcb03aa0",
      "needsInterop": true
    }
  },
  "chunks": {
    "chunk-O5RE5CKT": {
      "file": "chunk-O5RE5CKT.js"
    }
  }
}